qualitylib/__init__.py
qualitylib/_version.py
qualitylib/base.py
qualitylib/tests/__init__.py
qualitylib/tests/test_qualitylib.py
qualitylib-0.0.1.dist-info/AUTHORS.rst
qualitylib-0.0.1.dist-info/LICENSE
qualitylib-0.0.1.dist-info/METADATA
qualitylib-0.0.1.dist-info/WHEEL
qualitylib-0.0.1.dist-info/top_level.txt
qualitylib-0.0.1.dist-info/RECORD
