Metadata-Version: 2.1
Name: qualitylib
Version: 0.0.1
Summary: methods and methods for assessment of quality
Home-page: https://github.com/raamana/qualitylib
Author: Pradeep Reddy Raamana
Author-email: raamana@gmail.com
License: Apache Software License 2.0
Keywords: qualitylib
Platform: UNKNOWN
Classifier: Development Status :: 2 - Pre-Alpha
Classifier: Intended Audience :: Developers
Classifier: License :: OSI Approved :: Apache Software License
Classifier: Natural Language :: English
Classifier: Programming Language :: Python :: 3
Classifier: Programming Language :: Python :: 3.6
Classifier: Programming Language :: Python :: 3.7
Classifier: Programming Language :: Python :: 3.8
Requires-Python: >=3.6
